mcutils/__init__.py
mcutils/checksums.py
mcutils/decorators.py
mcutils/html.py
mcutils/http.py
mcutils/django/__init__.py
mcutils/django/cache.py
mcutils/django/debug.py
mcutils/django/decorators.py
mcutils/django/fields.py
mcutils/django/lock.py
mcutils/django/middleware.py
mcutils/django/models.py
mcutils/django/auth/__init__.py
mcutils/django/auth/backends/__init__.py
mcutils/django/auth/backends/ad.py
mcutils/django/auth/backends/email.py
mcutils/django/auth/backends/substuser.py
mcutils/django/mail/__init__.py
mcutils/django/mail/backends/__init__.py
mcutils/django/mail/backends/sendmail.py
mcutils/django/templatetags/__init__.py
mcutils/django/templatetags/collections_utils.py
mcutils/django/templatetags/compat_utils.py
mcutils/django/templatetags/form_utils.py
mcutils/django/templatetags/http_utils.py
metacorus_django_utils-1.1.6.dist-info/DESCRIPTION.rst
metacorus_django_utils-1.1.6.dist-info/METADATA
metacorus_django_utils-1.1.6.dist-info/RECORD
metacorus_django_utils-1.1.6.dist-info/WHEEL
metacorus_django_utils-1.1.6.dist-info/metadata.json
metacorus_django_utils-1.1.6.dist-info/top_level.txt
