Metadata-Version: 2.0
Name: metacorus-django-utils
Version: 1.1.6
Summary: UNKNOWN
Home-page: https://github.com/sprymak/metacorus-django-utils
Author: S.Prymak
Author-email: sprymak@metacorus.com
License: LICENSE
Platform: UNKNOWN
Requires-Dist: html5lib
Requires-Dist: simplejson
Requires-Dist: unidecode
